LICENSE
MANIFEST.in
README.rst
setup.py
docs/Makefile
docs/api.rst
docs/conf.py
docs/getting_started.rst
docs/index.rst
docs/installing.rst
docs/make.bat
docs/schema.jpg
docs/schema.rst
examples/stocks.py
redis_completion/__init__.py
redis_completion/engine.py
redis_completion/stop_words.py
redis_completion/tests.py
redis_completion.egg-info/PKG-INFO
redis_completion.egg-info/SOURCES.txt
redis_completion.egg-info/dependency_links.txt
redis_completion.egg-info/requires.txt
redis_completion.egg-info/top_level.txt