Metadata-Version: 1.1
Name: redis-completion
Version: 0.4.1
Summary: autocomplete with redis
Home-page: http://github.com/coleifer/redis-completion/tree/master
Author: Charles Leifer
Author-email: coleifer@gmail.com
License: UNKNOWN
Platform: UNKNOWN
Classifier: Development Status :: 4 - Beta
Classifier: Environment :: Web Environment
Classifier: Intended Audience :: Developers
Classifier: License :: OSI Approved :: MIT License
Classifier: Operating System :: OS Independent
Classifier: Programming Language :: Python
